betfair_ex_connection/__init__.py
betfair_ex_connection/betfair_ex_conn_class.py
betfair_ex_connection-0.1.4.dist-info/LICENSE
betfair_ex_connection-0.1.4.dist-info/METADATA
betfair_ex_connection-0.1.4.dist-info/WHEEL
betfair_ex_connection-0.1.4.dist-info/top_level.txt
betfair_ex_connection-0.1.4.dist-info/RECORD
