Metadata-Version: 2.1
Name: betfair-ex-connection
Version: 0.1.4
Summary: A package with functions for getting Betfair Exchange odds on upcoming Premier League matches.
Author: Jamie O'Brien
License: UNKNOWN
Platform: UNKNOWN
License-File: LICENSE
Requires-Dist: numpy
Requires-Dist: pandas
Requires-Dist: requests
